<?xml version="1.0" encoding="UTF-8"?>
<databaseChangeLog
        xmlns="http://www.liquibase.org/xml/ns/dbchangelog"
        xmlns:xsi="http://www.w3.org/2001/XMLSchema-instance"
        xsi:schemaLocation="http://www.liquibase.org/xml/ns/dbchangelog
        http://www.liquibase.org/xml/ns/dbchangelog/dbchangelog-3.8.xsd">

    <changeSet id="1" author="Pudul Aleksandr">
        <insert tableName="country">
            <column name="country_name" value="Канада" />
            <column name="country_code" value="+1" />
            <column name="iso_code" value="CA" />
        </insert>
        <insert tableName="country">
            <column name="country_name" value="Казахстан" />
            <column name="country_code" value="+7" />
            <column name="iso_code" value="KZ" />
        </insert>
        <insert tableName="country">
            <column name="country_name" value="Индонезия" />
            <column name="country_code" value="+62" />
            <column name="iso_code" value="ID" />
        </insert>
        <insert tableName="country">
            <column name="country_name" value="Филиппины" />
            <column name="country_code" value="+63" />
            <column name="iso_code" value="PH" />
        </insert>
        <insert tableName="country">
            <column name="country_name" value="Пакистан" />
            <column name="country_code" value="+92" />
            <column name="iso_code" value="PK" />
        </insert>
        <insert tableName="country">
            <column name="country_name" value="Бангладеш" />
            <column name="country_code" value="+880" />
            <column name="iso_code" value="BD" />
        </insert>
        <insert tableName="country">
            <column name="country_name" value="Чили" />
            <column name="country_code" value="+56" />
            <column name="iso_code" value="CL" />
        </insert>
        <insert tableName="country">
            <column name="country_name" value="Колумбия" />
            <column name="country_code" value="+57" />
            <column name="iso_code" value="CO" />
        </insert>
        <insert tableName="country">
            <column name="country_name" value="Перу" />
            <column name="country_code" value="+51" />
            <column name="iso_code" value="PE" />
        </insert>
        <insert tableName="country">
            <column name="country_name" value="Венесуэла" />
            <column name="country_code" value="+58" />
            <column name="iso_code" value="VE" />
        </insert>
        <insert tableName="country">
            <column name="country_name" value="Чехия" />
            <column name="country_code" value="+420" />
            <column name="iso_code" value="CZ" />
        </insert>
        <insert tableName="country">
            <column name="country_name" value="Венгрия" />
            <column name="country_code" value="+36" />
            <column name="iso_code" value="HU" />
        </insert>
        <insert tableName="country">
            <column name="country_name" value="Румыния" />
            <column name="country_code" value="+40" />
            <column name="iso_code" value="RO" />
        </insert>
        <insert tableName="country">
            <column name="country_name" value="Словакия" />
            <column name="country_code" value="+421" />
            <column name="iso_code" value="SK" />
        </insert>
    </changeSet>
</databaseChangeLog>